tail_recurse/__init__.py
tail_recurse-0.1.dist-info/METADATA
tail_recurse-0.1.dist-info/WHEEL
tail_recurse-0.1.dist-info/top_level.txt
tail_recurse-0.1.dist-info/RECORD
