Metadata-Version: 2.1
Name: tail-recurse
Version: 0.1
Summary: Tail Call Optimization Decorator for Python.
Home-page: https://github.com/brandon-rozek/tail-recurse
Author: Brandon Rozek
Author-email: hello@brandonrozek.com
License: UNKNOWN
Platform: UNKNOWN
Classifier: Programming Language :: Python :: 3
Classifier: License :: OSI Approved :: MIT License
Classifier: Operating System :: OS Independent
Requires-Python: >=3.7
